partnero/__init__.py
partnero/authentication.py
partnero/base_api.py
partnero/coupon_api.py
partnero/customer_api.py
partnero/partner_api.py
partnero/promotion_code_api.py
partnero/transaction_api.py
partnero/utils.py
partnero/webhook_api.py
partnero-0.4.0.dist-info/METADATA
partnero-0.4.0.dist-info/WHEEL
partnero-0.4.0.dist-info/RECORD
