Metadata-Version: 2.1
Name: partnero
Version: 0.4.0
Summary: A Python SDK designed to wrap around the Partnero API.
Home-page: https://github.com/simon-offerwell/partnero-sdk
License: MIT
Author: Simon Mahfoud
Author-email: simon@offerwell.com
Maintainer: Simon Mahfoud
Maintainer-email: simon@offerwell.com
Requires-Python: >=3.10,<4.0
Classifier: License :: OSI Approved :: MIT License
Classifier: Programming Language :: Python :: 3
Classifier: Programming Language :: Python :: 3.10
Classifier: Programming Language :: Python :: 3.11
Classifier: Programming Language :: Python :: 3.12
Requires-Dist: requests (>=2.31.0,<3.0.0)
Project-URL: Repository, https://github.com/simon-offerwell/partnero-sdk
